mastodonamnesia/__init__.py
mastodonamnesia/config.py
mastodonamnesia/mastodon_amnesia.py
mastodonamnesia/util.py
mastodonamnesia-2.2.2.dist-info/METADATA
mastodonamnesia-2.2.2.dist-info/WHEEL
mastodonamnesia-2.2.2.dist-info/entry_points.txt
mastodonamnesia-2.2.2.dist-info/LICENSE.md
mastodonamnesia-2.2.2.dist-info/RECORD
