Metadata-Version: 2.1
Name: mastodonamnesia
Version: 2.2.2
Summary: Renamed to Fedinesia. Use Fedinesia for future updates and bug fixes.
Home-page: https://codeberg.org/MarvinsMastodonTools/mastodonamnesia
License: AGPL-3.0-or-later
Author: marvin8
Author-email: marvin8@tuta.io
Requires-Python: >=3.9,<4.0
Classifier: License :: OSI Approved :: GNU Affero General Public License v3 or later (AGPLv3+)
Classifier: Programming Language :: Python :: 3
Classifier: Programming Language :: Python :: 3.9
Classifier: Programming Language :: Python :: 3.10
Classifier: Programming Language :: Python :: 3.11
Requires-Dist: aiocsv (>=1.2.3,<2.0.0)
Requires-Dist: aiofiles (>=0.8.0,<0.9.0)
Requires-Dist: arrow (>=1.2.1,<2.0.0)
Requires-Dist: click (>=8.1.3,<9.0.0)
Requires-Dist: minimal-activitypub (>=0.4.0,<0.5.0)
Requires-Dist: outdated (>=0.2.1,<0.3.0)
Requires-Dist: rich (>=13.0.0,<14.0.0)
Requires-Dist: tqdm (>=4.64.0,<5.0.0)
Requires-Dist: typing-extensions (>=4.2.0,<5.0.0)
Project-URL: Changelog, https://codeberg.org/MarvinsMastodonTools/mastodonamnesia/src/branch/main/CHANGELOG.rst
Project-URL: Repository, https://codeberg.org/MarvinsMastodonTools/mastodonamnesia
